terminal_agent/__init__.py
terminal_agent/agent.py
uta_av-0.1.1.dist-info/LICENSE
uta_av-0.1.1.dist-info/METADATA
uta_av-0.1.1.dist-info/WHEEL
uta_av-0.1.1.dist-info/entry_points.txt
uta_av-0.1.1.dist-info/top_level.txt
uta_av-0.1.1.dist-info/RECORD
