Metadata-Version: 2.1
Name: uta-av
Version: 0.1.1
Summary: A terminal agent for generating and executing Ubuntu commands for you.
Home-page: https://github.com/agentsvalley/uta-av
Author: Agents Valley
Author-email: agentsvalley@gmail.com
Classifier: Programming Language :: Python :: 3
Classifier: License :: OSI Approved :: MIT License
Classifier: Operating System :: POSIX :: Linux
Requires-Python: >=3.6
License-File: LICENSE
Requires-Dist: huggingface-hub>=0.14.1
